MANIFEST.in
README.rst
setup.cfg
setup.py
collective/__init__.py
collective.loremipsum.egg-info/PKG-INFO
collective.loremipsum.egg-info/SOURCES.txt
collective.loremipsum.egg-info/dependency_links.txt
collective.loremipsum.egg-info/entry_points.txt
collective.loremipsum.egg-info/namespace_packages.txt
collective.loremipsum.egg-info/not-zip-safe
collective.loremipsum.egg-info/requires.txt
collective.loremipsum.egg-info/top_level.txt
collective/loremipsum/__init__.py
collective/loremipsum/config.py
collective/loremipsum/configure.zcml
collective/loremipsum/fakeimagegetter.py
collective/loremipsum/interfaces.py
collective/loremipsum/permissions.py
collective/loremipsum/permissions.zcml
collective/loremipsum/testing.py
collective/loremipsum/utils.py
collective/loremipsum/vocabularies.py
collective/loremipsum/browser/__init__.py
collective/loremipsum/browser/configure.zcml
collective/loremipsum/browser/populate.py
collective/loremipsum/browser/views.py
collective/loremipsum/dummydata/memberdata.csv
collective/loremipsum/dummydata/readme.txt
collective/loremipsum/locales/es/LC_MESSAGES/collective.loremipsum.po
collective/loremipsum/locales/es/LC_MESSAGES/plone.po
collective/loremipsum/profiles/default/actions.xml
collective/loremipsum/profiles/default/browserlayer.xml
collective/loremipsum/profiles/default/metadata.xml
collective/loremipsum/profiles/default/rolemap.xml
docs/HISTORY.txt
docs/INSTALL.txt
docs/LICENSE.GPL
docs/LICENSE.txt