Metadata-Version: 1.1
Name: collective.loremipsum
Version: 0.10
Summary: Creates dummy content with populated Lorem Ipsum.
Home-page: https://github.com/collective/collective.loremipsum
Author: JC Brand
Author-email: jc@opkode.com
License: GPL
Keywords: dummy data
Platform: UNKNOWN
Classifier: Framework :: Plone :: 4.1
Classifier: Programming Language :: Python
